hextech_muscle/__init__.py
hextech_muscle/__main__.py
hextech_muscle/example.py
hextech_muscle/hextech.py
hextech_muscle-0.1.0.dist-info/LICENSE
hextech_muscle-0.1.0.dist-info/METADATA
hextech_muscle-0.1.0.dist-info/WHEEL
hextech_muscle-0.1.0.dist-info/entry_points.txt
hextech_muscle-0.1.0.dist-info/RECORD
