Metadata-Version: 2.1
Name: hextech-muscle
Version: 0.1.0
Summary: Hextronics HexTech Muscle serial control library
License: BSD-2-Clause
Author: Corey Matyas
Author-email: corey@hextronics.com
Requires-Python: >=3.11,<4.0
Classifier: License :: OSI Approved :: BSD License
Classifier: Operating System :: OS Independent
Classifier: Programming Language :: Python :: 3
Classifier: Programming Language :: Python :: 3.11
Classifier: Programming Language :: Python :: 3.12
Requires-Dist: pyserial (>=3.5,<4.0)
